stats_visual/__init__.py
stats_visual/distribution.py
stats_visual-1.0.1.dist-info/LICENSE.txt
stats_visual-1.0.1.dist-info/METADATA
stats_visual-1.0.1.dist-info/WHEEL
stats_visual-1.0.1.dist-info/top_level.txt
stats_visual-1.0.1.dist-info/RECORD
