Metadata-Version: 2.1
Name: stats-visual
Version: 1.0.1
Summary: package to visualize various statistical distributions
Author: Timotius Marselo
Author-email: timotiusmarselo@gmail.com
License-File: LICENSE.txt
